{
  "version": "7",
  "dialect": "postgresql",
  "entries": [
    {
      "idx": 0,
      "version": "7",
      "when": 1755039619394,
      "tag": "0000_unknown_rage",
      "breakpoints": true
    },
    {
      "idx": 1,
      "version": "7",
      "when": 1755039795949,
      "tag": "0001_mean_dormammu",
      "breakpoints": true
    },
    {
      "idx": 2,
      "version": "7",
      "when": 1755632741972,
      "tag": "0002_strong_wither",
      "breakpoints": true
    },
    {
      "idx": 3,
      "version": "7",
      "when": 1755632867356,
      "tag": "0003_sour_joseph",
      "breakpoints": true
    },
    {
      "idx": 4,
      "version": "7",
      "when": 1755723117343,
      "tag": "0004_cynical_mystique",
      "breakpoints": true
    },
    {
      "idx": 5,
      "version": "7",
      "when": 1755723731247,
      "tag": "0005_tranquil_azazel",
      "breakpoints": true
    },
    {
      "idx": 6,
      "version": "7",
      "when": 1755781242331,
      "tag": "0006_overjoyed_sentry",
      "breakpoints": true
    },
    {
      "idx": 7,
      "version": "7",
      "when": 1755781283447,
      "tag": "0007_useful_vindicator",
      "breakpoints": true
    },
    {
      "idx": 8,
      "version": "7",
      "when": 1755781384207,
      "tag": "0008_loose_slayback",
      "breakpoints": true
    },
    {
      "idx": 9,
      "version": "7",
      "when": 1755781720481,
      "tag": "0009_calm_whirlwind",
      "breakpoints": true
    }
  ]
}